notionfs/__init__.py
notionfs/__main__.py
notionfs/cli.py
notionfs/config.py
notionfs/converter/__init__.py
notionfs/converter/blocks_to_md.py
notionfs/converter/comments.py
notionfs/converter/diff.py
notionfs/converter/frontmatter.py
notionfs/converter/md_to_blocks.py
notionfs/converter/properties.py
notionfs/converter/schema.py
notionfs/notion/__init__.py
notionfs/notion/api_client.py
notionfs/notion/types.py
notionfs/sync/__init__.py
notionfs/sync/engine.py
notionfs/sync/progress.py
notionfs/sync/state.py
notionfs/sync/watcher.py
notionfs-0.4.0.dist-info/METADATA
notionfs-0.4.0.dist-info/WHEEL
notionfs-0.4.0.dist-info/entry_points.txt
notionfs-0.4.0.dist-info/licenses/LICENSE
notionfs-0.4.0.dist-info/RECORD
