Metadata-Version: 2.4
Name: notionfs
Version: 0.4.0
Summary: Local-first sync for Notion: work with pages as markdown files
Project-URL: Homepage, https://github.com/can1357/notionfs
Project-URL: Documentation, https://github.com/can1357/notionfs#readme
Project-URL: Repository, https://github.com/can1357/notionfs
Project-URL: Issues, https://github.com/can1357/notionfs/issues
Author: NotionFS Contributors
License: MIT
License-File: LICENSE
Keywords: cli,local-first,markdown,notion,sync
Classifier: Development Status :: 4 - Beta
Classifier: Environment :: Console
Classifier: Intended Audience :: Developers
Classifier: License :: OSI Approved :: MIT License
Classifier: Operating System :: OS Independent
Classifier: Programming Language :: Python :: 3
Classifier: Programming Language :: Python :: 3.11
Classifier: Programming Language :: Python :: 3.12
Classifier: Programming Language :: Python :: 3.13
Classifier: Topic :: Office/Business
Classifier: Topic :: Text Processing :: Markup :: Markdown
Requires-Python: >=3.11
Requires-Dist: aiosqlite>=0.19.0
Requires-Dist: click>=8.0
Requires-Dist: gitpython>=3.1.0
Requires-Dist: httpx>=0.25.0
Requires-Dist: mistune>=3.0.0
Requires-Dist: notion-client<2.5.0,>=2.0.0
Requires-Dist: python-dotenv>=1.0.0
Requires-Dist: python-frontmatter>=1.0
Requires-Dist: pyyaml>=6.0
Requires-Dist: questionary>=2.0.0
Requires-Dist: rich>=13.0
Requires-Dist: tomli-w>=1.0.0
Requires-Dist: trio>=0.25.0
Requires-Dist: watchfiles>=0.21.0
Provides-Extra: dev
Requires-Dist: mypy; extra == 'dev'
Requires-Dist: pytest; extra == 'dev'
Requires-Dist: pytest-asyncio; extra == 'dev'
Requires-Dist: pytest-cov; extra == 'dev'
Requires-Dist: pytest-trio; extra == 'dev'
Requires-Dist: ruff; extra == 'dev'
Requires-Dist: types-pyyaml; extra == 'dev'
